cg_learning_client/CGLearningClient.py
cg_learning_client/DataSet.py
cg_learning_client/__init__.py
cg_learning_client/utils/HttpUtil.py
cg_learning_client/utils/__init__.py
cg_learning_client-0.0.4.1.dist-info/METADATA
cg_learning_client-0.0.4.1.dist-info/WHEEL
cg_learning_client-0.0.4.1.dist-info/top_level.txt
cg_learning_client-0.0.4.1.dist-info/RECORD
